pow.py
setup.py
pow.egg-info/PKG-INFO
pow.egg-info/SOURCES.txt
pow.egg-info/dependency_links.txt
pow.egg-info/entry_points.txt
pow.egg-info/requires.txt
pow.egg-info/top_level.txt