Metadata-Version: 1.1
Name: pow
Version: 0.0.2
Summary: Command line text snippets, inspired by Zach Holman's **boom**.
Home-page: https://github.com/doctaphred/pow
Author: Frederick Wagner
Author-email: doctaphred@gmail.com
License: GPLv3
Keywords: command line,text,snippet,snippets,clipboard
Platform: UNKNOWN
Classifier: Development Status :: 2 - Pre-Alpha
Classifier: Programming Language :: Python :: 3.5
Classifier: Operating System :: MacOS :: MacOS X
Classifier: License :: OSI Approved :: GNU General Public License v3 (GPLv3)
